{
    "success": 1,
    "data": {
        "candlestick": [
            {
                "type": "1day",
                "ohlcv": [
                    [
                        "37738",
                        "37950",
                        "37598",
                        "37622",
                        "0.0000",
                        1420070400000
                    ],
                    [
                        "37682",
                        "38234",
                        "37458",
                        "38007",
                        "0.0000",
                        1420156800000
                    ],
                    [
                        "38007",
                        "38146",
                        "33739",
                        "33980",
                        "0.0000",
                        1420243200000
                    ],
                    [
                        "33739",
                        "34870",
                        "30726",
                        "31785",
                        "0.0000",
                        1420329600000
                    ],
                    [
                        "31815",
                        "33700",
                        "31758",
                        "33056",
                        "0.0000",
                        1420416000000
                    ],
                    [
                        "32985",
                        "33063",
                        "32723",
                        "32846",
                        "0.0000",
                        1420502400000
                    ],
                    [
                        "32871",
                        "33088",
                        "32871",
                        "33018",
                        "0.0000",
                        1420588800000
                    ],
                    [
                        "33064",
                        "33179",
                        "33064",
                        "33161",
                        "0.0000",
                        1420675200000
                    ],
                    [
                        "33166",
                        "36156",
                        "32297",
                        "34848",
                        "0.0000",
                        1420761600000
                    ],
                    [
                        "34839",
                        "34970",
                        "32129",
                        "32669",
                        "0.0000",
                        1420848000000
                    ],
                    [
                        "32670",
                        "33303",
                        "30987",
                        "31496",
                        "0.0000",
                        1420934400000
                    ],
                    [
                        "31509",
                        "32297",
                        "31278",
                        "31647",
                        "0.0000",
                        1421020800000
                    ],
                    [
                        "31473",
                        "31597",
                        "25580",
                        "26745",
                        "0.0000",
                        1421107200000
                    ],
                    [
                        "26713",
                        "27120",
                        "17844",
                        "20130",
                        "0.0000",
                        1421193600000
                    ],
                    [
                        "20238",
                        "27349",
                        "19827",
                        "24504",
                        "0.0000",
                        1421280000000
                    ],
                    [
                        "24513",
                        "26054",
                        "23180",
                        "24469",
                        "0.0000",
                        1421366400000
                    ],
                    [
                        "24468",
                        "25035",
                        "22604",
                        "23488",
                        "0.0000",
                        1421452800000
                    ],
                    [
                        "23488",
                        "26113",
                        "22939",
                        "24913",
                        "0.0000",
                        1421539200000
                    ],
                    [
                        "24877",
                        "25950",
                        "24349",
                        "25472",
                        "0.0000",
                        1421625600000
                    ],
                    [
                        "25475",
                        "25611",
                        "23930",
                        "24996",
                        "0.0000",
                        1421712000000
                    ],
                    [
                        "25137",
                        "26976",
                        "24084",
                        "26771",
                        "0.0000",
                        1421798400000
                    ],
                    [
                        "26876",
                        "28223",
                        "26670",
                        "27788",
                        "0.0000",
                        1421884800000
                    ],
                    [
                        "27739",
                        "28297",
                        "26685",
                        "27523",
                        "0.0000",
                        1421971200000
                    ],
                    [
                        "27497",
                        "29449",
                        "27097",
                        "29370",
                        "0.0000",
                        1422057600000
                    ],
                    [
                        "29371",
                        "30178",
                        "28428",
                        "29936",
                        "0.0000",
                        1422144000000
                    ],
                    [
                        "29957",
                        "36624",
                        "29957",
                        "32570",
                        "0.0000",
                        1422230400000
                    ],
                    [
                        "32586",
                        "33030",
                        "28689",
                        "31092",
                        "0.0000",
                        1422316800000
                    ],
                    [
                        "31102",
                        "31424",
                        "26541",
                        "27760",
                        "0.0000",
                        1422403200000
                    ],
                    [
                        "27790",
                        "28578",
                        "25980",
                        "27889",
                        "0.0000",
                        1422489600000
                    ],
                    [
                        "27798",
                        "28881",
                        "26506",
                        "26913",
                        "0.0000",
                        1422576000000
                    ],
                    [
                        "26911",
                        "27597",
                        "25358",
                        "25493",
                        "0.0000",
                        1422662400000
                    ],
                    [
                        "27223",
                        "27292",
                        "26444",
                        "26595",
                        "0.0000",
                        1422748800000
                    ],
                    [
                        "26640",
                        "28456",
                        "26024",
                        "28043",
                        "0.0000",
                        1422835200000
                    ],
                    [
                        "27947",
                        "28701",
                        "26318",
                        "26825",
                        "0.0000",
                        1422921600000
                    ],
                    [
                        "26850",
                        "27126",
                        "25860",
                        "26627",
                        "0.0000",
                        1423008000000
                    ],
                    [
                        "26593",
                        "26831",
                        "24720",
                        "25483",
                        "0.0000",
                        1423094400000
                    ],
                    [
                        "25426",
                        "26914",
                        "24719",
                        "26611",
                        "0.0000",
                        1423180800000
                    ],
                    [
                        "26619",
                        "27537",
                        "26420",
                        "27198",
                        "0.0000",
                        1423267200000
                    ],
                    [
                        "27255",
                        "27745",
                        "25885",
                        "26633",
                        "0.0000",
                        1423353600000
                    ],
                    [
                        "26628",
                        "26875",
                        "25524",
                        "26197",
                        "0.0000",
                        1423440000000
                    ],
                    [
                        "26165",
                        "26512",
                        "25551",
                        "26310",
                        "0.0000",
                        1423526400000
                    ],
                    [
                        "26322",
                        "26814",
                        "26126",
                        "26391",
                        "0.0000",
                        1423612800000
                    ],
                    [
                        "26377",
                        "26577",
                        "26083",
                        "26522",
                        "0.0000",
                        1423699200000
                    ],
                    [
                        "26549",
                        "28770",
                        "26302",
                        "28155",
                        "0.0000",
                        1423785600000
                    ],
                    [
                        "28155",
                        "30806",
                        "28143",
                        "30530",
                        "0.0000",
                        1423872000000
                    ],
                    [
                        "30509",
                        "31829",
                        "27056",
                        "27953",
                        "0.0000",
                        1423958400000
                    ],
                    [
                        "27944",
                        "28619",
                        "27184",
                        "27809",
                        "0.0000",
                        1424044800000
                    ],
                    [
                        "27769",
                        "29629",
                        "27452",
                        "29171",
                        "0.0000",
                        1424131200000
                    ],
                    [
                        "29162",
                        "29448",
                        "27580",
                        "28179",
                        "0.0000",
                        1424217600000
                    ],
                    [
                        "28186",
                        "29153",
                        "27934",
                        "28627",
                        "0.0000",
                        1424304000000
                    ],
                    [
                        "28645",
                        "29571",
                        "28468",
                        "29215",
                        "0.0000",
                        1424390400000
                    ],
                    [
                        "29158",
                        "29491",
                        "29039",
                        "29206",
                        "0.0000",
                        1424476800000
                    ],
                    [
                        "29258",
                        "29446",
                        "27668",
                        "28161",
                        "0.0000",
                        1424563200000
                    ],
                    [
                        "28139",
                        "28636",
                        "27591",
                        "28421",
                        "0.0000",
                        1424649600000
                    ],
                    [
                        "28492",
                        "28843",
                        "28153",
                        "28475",
                        "0.0000",
                        1424736000000
                    ],
                    [
                        "28425",
                        "28597",
                        "28037",
                        "28277",
                        "0.0000",
                        1424822400000
                    ],
                    [
                        "28339",
                        "28419",
                        "27808",
                        "28275",
                        "0.0000",
                        1424908800000
                    ],
                    [
                        "28253",
                        "30664",
                        "28166",
                        "30234",
                        "0.0000",
                        1424995200000
                    ],
                    [
                        "30175",
                        "30447",
                        "29327",
                        "30317",
                        "0.0000",
                        1425081600000
                    ],
                    [
                        "30762",
                        "31155",
                        "30488",
                        "30957",
                        "0.0000",
                        1425168000000
                    ],
                    [
                        "30918",
                        "33299",
                        "30622",
                        "33050",
                        "0.0000",
                        1425254400000
                    ],
                    [
                        "33134",
                        "34116",
                        "31755",
                        "33608",
                        "0.0000",
                        1425340800000
                    ],
                    [
                        "33590",
                        "33968",
                        "31711",
                        "32399",
                        "0.0000",
                        1425427200000
                    ],
                    [
                        "32426",
                        "33698",
                        "31523",
                        "32787",
                        "0.0000",
                        1425513600000
                    ],
                    [
                        "32833",
                        "33291",
                        "32268",
                        "32947",
                        "0.0000",
                        1425600000000
                    ],
                    [
                        "32939",
                        "33769",
                        "32623",
                        "33434",
                        "0.0000",
                        1425686400000
                    ],
                    [
                        "33434",
                        "33538",
                        "32759",
                        "33205",
                        "0.0000",
                        1425772800000
                    ],
                    [
                        "33211",
                        "35012",
                        "33128",
                        "34865",
                        "0.0000",
                        1425859200000
                    ],
                    [
                        "34860",
                        "35972",
                        "34476",
                        "35107",
                        "0.0000",
                        1425945600000
                    ],
                    [
                        "35172",
                        "36035",
                        "34686",
                        "36004",
                        "0.0000",
                        1426032000000
                    ],
                    [
                        "36032",
                        "36157",
                        "34971",
                        "35830",
                        "0.0000",
                        1426118400000
                    ],
                    [
                        "35903",
                        "35903",
                        "34371",
                        "34382",
                        "0.0000",
                        1426204800000
                    ],
                    [
                        "34380",
                        "34921",
                        "34043",
                        "34232",
                        "0.0000",
                        1426291200000
                    ],
                    [
                        "34278",
                        "34930",
                        "34160",
                        "34785",
                        "0.0000",
                        1426377600000
                    ],
                    [
                        "34815",
                        "35698",
                        "34679",
                        "35111",
                        "0.0000",
                        1426464000000
                    ],
                    [
                        "35120",
                        "35533",
                        "34210",
                        "34304",
                        "0.0000",
                        1426550400000
                    ],
                    [
                        "34312",
                        "34473",
                        "29940",
                        "30834",
                        "0.0000",
                        1426636800000
                    ],
                    [
                        "30720",
                        "32161",
                        "29899",
                        "31614",
                        "0.0000",
                        1426723200000
                    ],
                    [
                        "31626",
                        "32034",
                        "30885",
                        "31453",
                        "0.0000",
                        1426809600000
                    ],
                    [
                        "31450",
                        "31517",
                        "30768",
                        "31218",
                        "0.0000",
                        1426896000000
                    ],
                    [
                        "31218",
                        "32646",
                        "31127",
                        "32135",
                        "0.0000",
                        1426982400000
                    ],
                    [
                        "32174",
                        "32389",
                        "31071",
                        "31850",
                        "0.0000",
                        1427068800000
                    ],
                    [
                        "31863",
                        "31927",
                        "28946",
                        "29348",
                        "0.0000",
                        1427155200000
                    ],
                    [
                        "29435",
                        "29861",
                        "28279",
                        "29513",
                        "0.0000",
                        1427241600000
                    ],
                    [
                        "29489",
                        "30241",
                        "29057",
                        "29709",
                        "0.0000",
                        1427328000000
                    ],
                    [
                        "29694",
                        "29865",
                        "29175",
                        "29536",
                        "0.0000",
                        1427414400000
                    ],
                    [
                        "29535",
                        "30238",
                        "29454",
                        "30124",
                        "0.0000",
                        1427500800000
                    ],
                    [
                        "30128",
                        "30134",
                        "28611",
                        "28858",
                        "0.0000",
                        1427587200000
                    ],
                    [
                        "28882",
                        "29893",
                        "28207",
                        "29760",
                        "0.0000",
                        1427673600000
                    ],
                    [
                        "29782",
                        "29897",
                        "28625",
                        "29304",
                        "0.0000",
                        1427760000000
                    ],
                    [
                        "29200",
                        "29536",
                        "28742",
                        "29500",
                        "0.0000",
                        1427846400000
                    ],
                    [
                        "29510",
                        "30770",
                        "29237",
                        "30316",
                        "0.0000",
                        1427932800000
                    ],
                    [
                        "30304",
                        "30720",
                        "30059",
                        "30247",
                        "0.0000",
                        1428019200000
                    ],
                    [
                        "30247",
                        "30444",
                        "29838",
                        "30188",
                        "0.0000",
                        1428105600000
                    ],
                    [
                        "30176",
                        "31026",
                        "29944",
                        "30969",
                        "0.0000",
                        1428192000000
                    ],
                    [
                        "31016",
                        "31328",
                        "30354",
                        "30537",
                        "0.0000",
                        1428278400000
                    ],
                    [
                        "30558",
                        "30828",
                        "30145",
                        "30518",
                        "0.0000",
                        1428364800000
                    ],
                    [
                        "30503",
                        "30629",
                        "29140",
                        "29375",
                        "0.0000",
                        1428451200000
                    ],
                    [
                        "29456",
                        "29635",
                        "28672",
                        "29347",
                        "0.0000",
                        1428537600000
                    ],
                    [
                        "29372",
                        "29392",
                        "27778",
                        "28366",
                        "0.0000",
                        1428624000000
                    ],
                    [
                        "28366",
                        "28778",
                        "28006",
                        "28385",
                        "0.0000",
                        1428710400000
                    ],
                    [
                        "28378",
                        "28547",
                        "28057",
                        "28428",
                        "0.0000",
                        1428796800000
                    ],
                    [
                        "28417",
                        "28542",
                        "26385",
                        "26789",
                        "0.0000",
                        1428883200000
                    ],
                    [
                        "26721",
                        "26947",
                        "25061",
                        "25778",
                        "0.0000",
                        1428969600000
                    ],
                    [
                        "25808",
                        "26582",
                        "25589",
                        "26548",
                        "0.0000",
                        1429056000000
                    ],
                    [
                        "26512",
                        "27322",
                        "26466",
                        "27086",
                        "0.0000",
                        1429142400000
                    ],
                    [
                        "27051",
                        "27183",
                        "26116",
                        "26471",
                        "0.0000",
                        1429228800000
                    ],
                    [
                        "26471",
                        "26723",
                        "26200",
                        "26567",
                        "0.0000",
                        1429315200000
                    ],
                    [
                        "26561",
                        "27036",
                        "26389",
                        "26448",
                        "0.0000",
                        1429401600000
                    ],
                    [
                        "26474",
                        "26974",
                        "26326",
                        "26735",
                        "0.0000",
                        1429488000000
                    ],
                    [
                        "26762",
                        "28240",
                        "26732",
                        "28209",
                        "0.0000",
                        1429574400000
                    ],
                    [
                        "28216",
                        "28610",
                        "27471",
                        "28017",
                        "0.0000",
                        1429660800000
                    ],
                    [
                        "27998",
                        "28336",
                        "27801",
                        "28216",
                        "0.0000",
                        1429747200000
                    ],
                    [
                        "28150",
                        "28196",
                        "27142",
                        "27391",
                        "0.0000",
                        1429833600000
                    ],
                    [
                        "27486",
                        "27635",
                        "26851",
                        "26901",
                        "0.0000",
                        1429920000000
                    ],
                    [
                        "26901",
                        "27036",
                        "25575",
                        "26107",
                        "0.0000",
                        1430006400000
                    ],
                    [
                        "26112",
                        "27386",
                        "25939",
                        "27070",
                        "0.0000",
                        1430092800000
                    ],
                    [
                        "27066",
                        "27113",
                        "26334",
                        "26756",
                        "0.0000",
                        1430179200000
                    ],
                    [
                        "26748",
                        "27016",
                        "26417",
                        "26828",
                        "0.0000",
                        1430265600000
                    ],
                    [
                        "26834",
                        "28649",
                        "26703",
                        "28221",
                        "0.0000",
                        1430352000000
                    ],
                    [
                        "28298",
                        "28656",
                        "27710",
                        "27769",
                        "0.0000",
                        1430438400000
                    ],
                    [
                        "27775",
                        "28237",
                        "27633",
                        "28109",
                        "0.0000",
                        1430524800000
                    ],
                    [
                        "28109",
                        "29121",
                        "27926",
                        "28714",
                        "0.0000",
                        1430611200000
                    ],
                    [
                        "28807",
                        "29089",
                        "28357",
                        "28629",
                        "0.0000",
                        1430697600000
                    ],
                    [
                        "28621",
                        "28688",
                        "27624",
                        "28205",
                        "0.0000",
                        1430784000000
                    ],
                    [
                        "28214",
                        "28305",
                        "27113",
                        "27281",
                        "0.0000",
                        1430870400000
                    ],
                    [
                        "27264",
                        "28746",
                        "27076",
                        "28358",
                        "0.0000",
                        1430956800000
                    ],
                    [
                        "28392",
                        "29539",
                        "28226",
                        "29134",
                        "0.0000",
                        1431043200000
                    ],
                    [
                        "29136",
                        "29590",
                        "28585",
                        "28985",
                        "0.0000",
                        1431129600000
                    ],
                    [
                        "28967",
                        "29348",
                        "28513",
                        "28650",
                        "0.0000",
                        1431216000000
                    ],
                    [
                        "28636",
                        "29362",
                        "28534",
                        "28986",
                        "0.0000",
                        1431302400000
                    ],
                    [
                        "28986",
                        "29069",
                        "28528",
                        "28888",
                        "0.0000",
                        1431388800000
                    ],
                    [
                        "28867",
                        "29115",
                        "28003",
                        "28126",
                        "0.0000",
                        1431475200000
                    ],
                    [
                        "28145",
                        "28568",
                        "27678",
                        "28271",
                        "0.0000",
                        1431561600000
                    ],
                    [
                        "28300",
                        "28546",
                        "28061",
                        "28330",
                        "0.0000",
                        1431648000000
                    ],
                    [
                        "28332",
                        "28333",
                        "27927",
                        "28126",
                        "0.0000",
                        1431734400000
                    ],
                    [
                        "28072",
                        "28285",
                        "27945",
                        "28164",
                        "0.0000",
                        1431820800000
                    ],
                    [
                        "28198",
                        "28393",
                        "27769",
                        "27925",
                        "0.0000",
                        1431907200000
                    ],
                    [
                        "27939",
                        "28150",
                        "27765",
                        "27917",
                        "0.0000",
                        1431993600000
                    ],
                    [
                        "27970",
                        "28473",
                        "27939",
                        "28397",
                        "0.0000",
                        1432080000000
                    ],
                    [
                        "28380",
                        "28609",
                        "28296",
                        "28448",
                        "0.0000",
                        1432166400000
                    ],
                    [
                        "28428",
                        "29277",
                        "28154",
                        "29046",
                        "0.0000",
                        1432252800000
                    ],
                    [
                        "29022",
                        "29250",
                        "28852",
                        "28925",
                        "0.0000",
                        1432339200000
                    ],
                    [
                        "28907",
                        "29368",
                        "28884",
                        "29081",
                        "0.0000",
                        1432425600000
                    ],
                    [
                        "29169",
                        "29220",
                        "28319",
                        "28661",
                        "0.0000",
                        1432512000000
                    ],
                    [
                        "28691",
                        "29254",
                        "28670",
                        "28991",
                        "0.0000",
                        1432598400000
                    ],
                    [
                        "28998",
                        "29345",
                        "28935",
                        "29099",
                        "0.0000",
                        1432684800000
                    ],
                    [
                        "29107",
                        "29433",
                        "29077",
                        "29276",
                        "0.0000",
                        1432771200000
                    ],
                    [
                        "29270",
                        "29325",
                        "28957",
                        "29302",
                        "0.0000",
                        1432857600000
                    ],
                    [
                        "29302",
                        "29302",
                        "28678",
                        "28816",
                        "0.0000",
                        1432944000000
                    ],
                    [
                        "28816",
                        "28865",
                        "28312",
                        "28441",
                        "0.0000",
                        1433030400000
                    ],
                    [
                        "28436",
                        "28698",
                        "27530",
                        "27909",
                        "0.0000",
                        1433116800000
                    ],
                    [
                        "27940",
                        "28196",
                        "27588",
                        "27935",
                        "0.0000",
                        1433203200000
                    ],
                    [
                        "27957",
                        "28199",
                        "27673",
                        "27878",
                        "0.0000",
                        1433289600000
                    ],
                    [
                        "27965",
                        "28109",
                        "27616",
                        "27739",
                        "0.0000",
                        1433376000000
                    ],
                    [
                        "27778",
                        "28290",
                        "27325",
                        "28184",
                        "0.0000",
                        1433462400000
                    ],
                    [
                        "28197",
                        "28292",
                        "28017",
                        "28259",
                        "0.0000",
                        1433548800000
                    ],
                    [
                        "28253",
                        "28320",
                        "27865",
                        "27977",
                        "0.0000",
                        1433635200000
                    ],
                    [
                        "27962",
                        "28576",
                        "27857",
                        "28426",
                        "0.0000",
                        1433721600000
                    ],
                    [
                        "28418",
                        "28684",
                        "28186",
                        "28441",
                        "0.0000",
                        1433808000000
                    ],
                    [
                        "28451",
                        "28482",
                        "27828",
                        "28003",
                        "0.0000",
                        1433894400000
                    ],
                    [
                        "28036",
                        "28380",
                        "27958",
                        "28308",
                        "0.0000",
                        1433980800000
                    ],
                    [
                        "28291",
                        "28492",
                        "28205",
                        "28310",
                        "0.0000",
                        1434067200000
                    ],
                    [
                        "28297",
                        "28635",
                        "28144",
                        "28586",
                        "0.0000",
                        1434153600000
                    ],
                    [
                        "28586",
                        "28877",
                        "28482",
                        "28616",
                        "0.0000",
                        1434240000000
                    ],
                    [
                        "28657",
                        "29255",
                        "28591",
                        "29118",
                        "0.0000",
                        1434326400000
                    ],
                    [
                        "29128",
                        "31102",
                        "28928",
                        "30876",
                        "0.0000",
                        1434412800000
                    ],
                    [
                        "30859",
                        "31882",
                        "30031",
                        "30617",
                        "0.0000",
                        1434499200000
                    ],
                    [
                        "30551",
                        "30875",
                        "29473",
                        "30554",
                        "0.0000",
                        1434585600000
                    ],
                    [
                        "30529",
                        "30730",
                        "29713",
                        "29904",
                        "0.0000",
                        1434672000000
                    ],
                    [
                        "29910",
                        "30132",
                        "29442",
                        "30034",
                        "0.0000",
                        1434758400000
                    ],
                    [
                        "30021",
                        "30064",
                        "29580",
                        "29908",
                        "0.0000",
                        1434844800000
                    ],
                    [
                        "29887",
                        "30594",
                        "29844",
                        "30362",
                        "0.0000",
                        1434931200000
                    ],
                    [
                        "30367",
                        "30585",
                        "30046",
                        "30193",
                        "0.0000",
                        1435017600000
                    ],
                    [
                        "30212",
                        "30241",
                        "29596",
                        "29751",
                        "0.0000",
                        1435104000000
                    ],
                    [
                        "29752",
                        "30059",
                        "29591",
                        "29908",
                        "0.0000",
                        1435190400000
                    ],
                    [
                        "29907",
                        "30149",
                        "29625",
                        "30092",
                        "0.0000",
                        1435276800000
                    ],
                    [
                        "30092",
                        "31209",
                        "30015",
                        "31111",
                        "0.0000",
                        1435363200000
                    ],
                    [
                        "31120",
                        "31120",
                        "30402",
                        "30479",
                        "0.0000",
                        1435449600000
                    ],
                    [
                        "30571",
                        "31589",
                        "30490",
                        "31408",
                        "0.0000",
                        1435536000000
                    ],
                    [
                        "31355",
                        "32798",
                        "31234",
                        "32136",
                        "0.0000",
                        1435622400000
                    ],
                    [
                        "32176",
                        "32501",
                        "31198",
                        "31773",
                        "0.0000",
                        1435708800000
                    ],
                    [
                        "31783",
                        "32168",
                        "31161",
                        "31325",
                        "0.0000",
                        1435795200000
                    ],
                    [
                        "31296",
                        "31533",
                        "31023",
                        "31420",
                        "0.0000",
                        1435881600000
                    ],
                    [
                        "31439",
                        "32078",
                        "31190",
                        "31962",
                        "0.0000",
                        1435968000000
                    ],
                    [
                        "31940",
                        "33730",
                        "31767",
                        "33239",
                        "0.0000",
                        1436054400000
                    ],
                    [
                        "33244",
                        "34131",
                        "32679",
                        "32938",
                        "0.0000",
                        1436140800000
                    ],
                    [
                        "32976",
                        "33325",
                        "32313",
                        "32535",
                        "0.0000",
                        1436227200000
                    ],
                    [
                        "32501",
                        "33076",
                        "32049",
                        "32717",
                        "0.0000",
                        1436313600000
                    ],
                    [
                        "32641",
                        "32983",
                        "32191",
                        "32739",
                        "0.0000",
                        1436400000000
                    ],
                    [
                        "32738",
                        "36205",
                        "32696",
                        "35026",
                        "0.0000",
                        1436486400000
                    ],
                    [
                        "34952",
                        "36600",
                        "34860",
                        "35813",
                        "0.0000",
                        1436572800000
                    ],
                    [
                        "35814",
                        "39049",
                        "35814",
                        "38045",
                        "0.0000",
                        1436659200000
                    ],
                    [
                        "38049",
                        "38084",
                        "34684",
                        "36179",
                        "0.0000",
                        1436745600000
                    ],
                    [
                        "36179",
                        "36673",
                        "35309",
                        "35466",
                        "0.0000",
                        1436832000000
                    ],
                    [
                        "35456",
                        "36345",
                        "35228",
                        "35399",
                        "0.0000",
                        1436918400000
                    ],
                    [
                        "35393",
                        "36227",
                        "34110",
                        "34506",
                        "0.0000",
                        1437004800000
                    ],
                    [
                        "34497",
                        "34828",
                        "33769",
                        "34667",
                        "0.0000",
                        1437091200000
                    ],
                    [
                        "34632",
                        "35110",
                        "34332",
                        "34340",
                        "0.0000",
                        1437177600000
                    ],
                    [
                        "34333",
                        "34502",
                        "34140",
                        "34186",
                        "0.0000",
                        1437264000000
                    ],
                    [
                        "34139",
                        "34724",
                        "34098",
                        "34721",
                        "0.0000",
                        1437350400000
                    ],
                    [
                        "34689",
                        "34977",
                        "34223",
                        "34283",
                        "0.0000",
                        1437436800000
                    ],
                    [
                        "34239",
                        "34487",
                        "34016",
                        "34451",
                        "0.0000",
                        1437523200000
                    ],
                    [
                        "34433",
                        "34547",
                        "34162",
                        "34269",
                        "0.0000",
                        1437609600000
                    ],
                    [
                        "34295",
                        "35969",
                        "34186",
                        "35780",
                        "0.0000",
                        1437696000000
                    ],
                    [
                        "35779",
                        "36151",
                        "35470",
                        "35752",
                        "0.0000",
                        1437782400000
                    ],
                    [
                        "35775",
                        "36398",
                        "35582",
                        "36288",
                        "0.0000",
                        1437868800000
                    ],
                    [
                        "36211",
                        "36663",
                        "35315",
                        "36279",
                        "0.0000",
                        1437955200000
                    ],
                    [
                        "36201",
                        "36668",
                        "36125",
                        "36332",
                        "0.0000",
                        1438041600000
                    ],
                    [
                        "36320",
                        "36390",
                        "35513",
                        "35926",
                        "0.0000",
                        1438128000000
                    ],
                    [
                        "35956",
                        "36014",
                        "35377",
                        "35735",
                        "0.0000",
                        1438214400000
                    ],
                    [
                        "35760",
                        "35835",
                        "34971",
                        "35217",
                        "0.0000",
                        1438300800000
                    ],
                    [
                        "34872",
                        "35063",
                        "34823",
                        "35020",
                        "0.0000",
                        1438473600000
                    ],
                    [
                        "35042",
                        "35497",
                        "34657",
                        "34760",
                        "0.0000",
                        1438560000000
                    ],
                    [
                        "34782",
                        "35502",
                        "34761",
                        "35423",
                        "0.0000",
                        1438646400000
                    ],
                    [
                        "35419",
                        "35563",
                        "34878",
                        "35079",
                        "0.0000",
                        1438732800000
                    ],
                    [
                        "35090",
                        "35147",
                        "34489",
                        "34617",
                        "0.0000",
                        1438819200000
                    ],
                    [
                        "34609",
                        "34921",
                        "34217",
                        "34735",
                        "0.0000",
                        1438905600000
                    ],
                    [
                        "34773",
                        "34777",
                        "32347",
                        "32569",
                        "0.0000",
                        1438992000000
                    ],
                    [
                        "32569",
                        "33408",
                        "32422",
                        "32956",
                        "0.0000",
                        1439078400000
                    ],
                    [
                        "32972",
                        "33265",
                        "32601",
                        "32945",
                        "0.0000",
                        1439164800000
                    ],
                    [
                        "32909",
                        "33963",
                        "32909",
                        "33920",
                        "0.0000",
                        1439251200000
                    ],
                    [
                        "33923",
                        "33950",
                        "32989",
                        "33279",
                        "0.0000",
                        1439337600000
                    ],
                    [
                        "33258",
                        "33321",
                        "32636",
                        "32900",
                        "0.0000",
                        1439424000000
                    ],
                    [
                        "32933",
                        "33193",
                        "32599",
                        "33010",
                        "0.0000",
                        1439510400000
                    ],
                    [
                        "33019",
                        "33135",
                        "32383",
                        "32508",
                        "0.0000",
                        1439596800000
                    ],
                    [
                        "32508",
                        "32600",
                        "31582",
                        "31852",
                        "0.0000",
                        1439683200000
                    ],
                    [
                        "31858",
                        "32237",
                        "31656",
                        "31917",
                        "0.0000",
                        1439769600000
                    ],
                    [
                        "31944",
                        "31985",
                        "27504",
                        "27963",
                        "0.0000",
                        1439856000000
                    ],
                    [
                        "27853",
                        "29544",
                        "27505",
                        "28123",
                        "0.0000",
                        1439942400000
                    ],
                    [
                        "28041",
                        "29341",
                        "28041",
                        "29078",
                        "0.0000",
                        1440028800000
                    ],
                    [
                        "29030",
                        "29101",
                        "28266",
                        "28493",
                        "0.0000",
                        1440115200000
                    ],
                    [
                        "28504",
                        "28702",
                        "27214",
                        "28189",
                        "0.0000",
                        1440201600000
                    ],
                    [
                        "28189",
                        "28559",
                        "27561",
                        "27863",
                        "0.0000",
                        1440288000000
                    ],
                    [
                        "27779",
                        "27857",
                        "24708",
                        "24933",
                        "0.0000",
                        1440374400000
                    ],
                    [
                        "24920",
                        "27108",
                        "23603",
                        "26368",
                        "0.0000",
                        1440460800000
                    ],
                    [
                        "26476",
                        "27678",
                        "26279",
                        "27109",
                        "0.0000",
                        1440547200000
                    ],
                    [
                        "27095",
                        "27697",
                        "26763",
                        "27241",
                        "0.0000",
                        1440633600000
                    ],
                    [
                        "27277",
                        "28637",
                        "26681",
                        "28199",
                        "0.0000",
                        1440720000000
                    ],
                    [
                        "28212",
                        "28473",
                        "27593",
                        "28064",
                        "0.0000",
                        1440806400000
                    ],
                    [
                        "28048",
                        "28333",
                        "27394",
                        "27778",
                        "0.0000",
                        1440892800000
                    ],
                    [
                        "27754",
                        "28183",
                        "27212",
                        "27838",
                        "0.0000",
                        1440979200000
                    ],
                    [
                        "27853",
                        "27980",
                        "27041",
                        "27292",
                        "0.0000",
                        1441065600000
                    ],
                    [
                        "27434",
                        "27748",
                        "27119",
                        "27646",
                        "0.0000",
                        1441152000000
                    ],
                    [
                        "27617",
                        "27723",
                        "27189",
                        "27300",
                        "0.0000",
                        1441238400000
                    ],
                    [
                        "27223",
                        "27544",
                        "26995",
                        "27436",
                        "0.0000",
                        1441324800000
                    ],
                    [
                        "27460",
                        "28233",
                        "27282",
                        "28041",
                        "0.0000",
                        1441411200000
                    ],
                    [
                        "28016",
                        "29064",
                        "27972",
                        "28630",
                        "0.0000",
                        1441497600000
                    ],
                    [
                        "28626",
                        "28997",
                        "28470",
                        "28686",
                        "0.0000",
                        1441584000000
                    ],
                    [
                        "28666",
                        "29549",
                        "28633",
                        "29331",
                        "0.0000",
                        1441670400000
                    ],
                    [
                        "29353",
                        "29399",
                        "28560",
                        "28658",
                        "0.0000",
                        1441756800000
                    ],
                    [
                        "28663",
                        "29197",
                        "28339",
                        "28798",
                        "0.0000",
                        1441843200000
                    ],
                    [
                        "28816",
                        "29115",
                        "28654",
                        "28939",
                        "0.0000",
                        1441929600000
                    ],
                    [
                        "28929",
                        "28939",
                        "28097",
                        "28311",
                        "0.0000",
                        1442016000000
                    ],
                    [
                        "28311",
                        "28467",
                        "27492",
                        "27745",
                        "0.0000",
                        1442102400000
                    ],
                    [
                        "27706",
                        "27972",
                        "26978",
                        "27648",
                        "0.0000",
                        1442188800000
                    ],
                    [
                        "27721",
                        "27843",
                        "27096",
                        "27701",
                        "0.0000",
                        1442275200000
                    ],
                    [
                        "27685",
                        "27721",
                        "26844",
                        "27525",
                        "0.0000",
                        1442361600000
                    ],
                    [
                        "27522",
                        "28423",
                        "27426",
                        "27883",
                        "0.0000",
                        1442448000000
                    ],
                    [
                        "27816",
                        "28116",
                        "27526",
                        "27971",
                        "0.0000",
                        1442534400000
                    ],
                    [
                        "27985",
                        "28048",
                        "27583",
                        "27597",
                        "0.0000",
                        1442620800000
                    ],
                    [
                        "27597",
                        "27801",
                        "27481",
                        "27622",
                        "0.0000",
                        1442707200000
                    ],
                    [
                        "27574",
                        "27574",
                        "27066",
                        "27253",
                        "0.0000",
                        1442793600000
                    ],
                    [
                        "27236",
                        "27830",
                        "26795",
                        "27670",
                        "0.0000",
                        1442880000000
                    ],
                    [
                        "27671",
                        "27841",
                        "27408",
                        "27583",
                        "0.0000",
                        1442966400000
                    ],
                    [
                        "27566",
                        "28286",
                        "27417",
                        "28127",
                        "0.0000",
                        1443052800000
                    ],
                    [
                        "28140",
                        "28701",
                        "27938",
                        "28345",
                        "0.0000",
                        1443139200000
                    ],
                    [
                        "28358",
                        "28422",
                        "28100",
                        "28198",
                        "0.0000",
                        1443225600000
                    ],
                    [
                        "28198",
                        "28294",
                        "27857",
                        "27981",
                        "0.0000",
                        1443312000000
                    ],
                    [
                        "27990",
                        "28735",
                        "27905",
                        "28655",
                        "0.0000",
                        1443398400000
                    ],
                    [
                        "28627",
                        "28797",
                        "28214",
                        "28405",
                        "0.0000",
                        1443484800000
                    ],
                    [
                        "28409",
                        "28562",
                        "28196",
                        "28315",
                        "0.0000",
                        1443571200000
                    ],
                    [
                        "28276",
                        "28719",
                        "28179",
                        "28417",
                        "0.0000",
                        1443657600000
                    ],
                    [
                        "28542",
                        "28737",
                        "28142",
                        "28517",
                        "0.0000",
                        1443744000000
                    ],
                    [
                        "28517",
                        "28768",
                        "28341",
                        "28659",
                        "0.0000",
                        1443830400000
                    ],
                    [
                        "28672",
                        "28782",
                        "28512",
                        "28642",
                        "0.0000",
                        1443916800000
                    ],
                    [
                        "28634",
                        "29017",
                        "28401",
                        "29016",
                        "0.0000",
                        1444003200000
                    ],
                    [
                        "29014",
                        "29828",
                        "28851",
                        "29651",
                        "0.0000",
                        1444089600000
                    ],
                    [
                        "29694",
                        "29799",
                        "29063",
                        "29168",
                        "0.0000",
                        1444176000000
                    ],
                    [
                        "29220",
                        "29367",
                        "28993",
                        "29134",
                        "0.0000",
                        1444262400000
                    ],
                    [
                        "29181",
                        "29451",
                        "29051",
                        "29392",
                        "0.0000",
                        1444348800000
                    ],
                    [
                        "29393",
                        "29627",
                        "29214",
                        "29540",
                        "0.0000",
                        1444435200000
                    ],
                    [
                        "29540",
                        "29876",
                        "29398",
                        "29814",
                        "0.0000",
                        1444521600000
                    ],
                    [
                        "29796",
                        "29855",
                        "29423",
                        "29508",
                        "0.0000",
                        1444608000000
                    ],
                    [
                        "29487",
                        "30043",
                        "29095",
                        "29906",
                        "0.0000",
                        1444694400000
                    ],
                    [
                        "29875",
                        "30409",
                        "29642",
                        "30007",
                        "0.0000",
                        1444780800000
                    ],
                    [
                        "30033",
                        "30524",
                        "29652",
                        "30305",
                        "0.0000",
                        1444867200000
                    ],
                    [
                        "30303",
                        "31853",
                        "30208",
                        "31426",
                        "0.0000",
                        1444953600000
                    ],
                    [
                        "31426",
                        "32610",
                        "31153",
                        "32260",
                        "0.0000",
                        1445040000000
                    ],
                    [
                        "32256",
                        "32391",
                        "31029",
                        "31143",
                        "0.0000",
                        1445126400000
                    ],
                    [
                        "31138",
                        "31783",
                        "31015",
                        "31510",
                        "0.0000",
                        1445212800000
                    ],
                    [
                        "31581",
                        "32729",
                        "31378",
                        "32421",
                        "0.0000",
                        1445299200000
                    ],
                    [
                        "32409",
                        "32691",
                        "31681",
                        "32110",
                        "0.0000",
                        1445385600000
                    ],
                    [
                        "32111",
                        "33544",
                        "32028",
                        "33270",
                        "0.0000",
                        1445472000000
                    ],
                    [
                        "33270",
                        "33889",
                        "33087",
                        "33841",
                        "0.0000",
                        1445558400000
                    ],
                    [
                        "33881",
                        "34497",
                        "33795",
                        "34356",
                        "0.0000",
                        1445644800000
                    ],
                    [
                        "34379",
                        "35954",
                        "34279",
                        "34450",
                        "0.0000",
                        1445731200000
                    ],
                    [
                        "34406",
                        "34708",
                        "33818",
                        "34706",
                        "0.0000",
                        1445817600000
                    ],
                    [
                        "34643",
                        "36111",
                        "34525",
                        "35608",
                        "0.0000",
                        1445904000000
                    ],
                    [
                        "35597",
                        "37195",
                        "35428",
                        "36950",
                        "0.0000",
                        1445990400000
                    ],
                    [
                        "36900",
                        "38704",
                        "36421",
                        "38107",
                        "0.0000",
                        1446076800000
                    ],
                    [
                        "38078",
                        "40336",
                        "37837",
                        "39637",
                        "0.0000",
                        1446163200000
                    ],
                    [
                        "39595",
                        "40365",
                        "36544",
                        "37412",
                        "0.0000",
                        1446249600000
                    ],
                    [
                        "39191",
                        "39743",
                        "38942",
                        "39258",
                        "0.0000",
                        1446336000000
                    ],
                    [
                        "39257",
                        "44578",
                        "38543",
                        "43640",
                        "0.0000",
                        1446422400000
                    ],
                    [
                        "43706",
                        "50932",
                        "43546",
                        "48925",
                        "0.0000",
                        1446508800000
                    ],
                    [
                        "49062",
                        "60936",
                        "44731",
                        "49584",
                        "0.0000",
                        1446595200000
                    ],
                    [
                        "49572",
                        "54526",
                        "44343",
                        "46913",
                        "0.0000",
                        1446681600000
                    ],
                    [
                        "47235",
                        "48864",
                        "43030",
                        "46107",
                        "0.0000",
                        1446768000000
                    ],
                    [
                        "46027",
                        "48366",
                        "45688",
                        "47252",
                        "0.0000",
                        1446854400000
                    ],
                    [
                        "47234",
                        "48077",
                        "45156",
                        "45910",
                        "0.0000",
                        1446940800000
                    ],
                    [
                        "45990",
                        "47763",
                        "44512",
                        "46501",
                        "0.0000",
                        1447027200000
                    ],
                    [
                        "46556",
                        "46979",
                        "39875",
                        "41456",
                        "0.0000",
                        1447113600000
                    ],
                    [
                        "41219",
                        "42006",
                        "36101",
                        "38042",
                        "0.0000",
                        1447200000000
                    ],
                    [
                        "38076",
                        "42418",
                        "37882",
                        "41309",
                        "0.0000",
                        1447286400000
                    ],
                    [
                        "41296",
                        "41966",
                        "39839",
                        "41322",
                        "0.0000",
                        1447372800000
                    ],
                    [
                        "41320",
                        "43665",
                        "39907",
                        "40832",
                        "0.0000",
                        1447459200000
                    ],
                    [
                        "40722",
                        "41076",
                        "38552",
                        "39049",
                        "0.0000",
                        1447545600000
                    ],
                    [
                        "39117",
                        "40956",
                        "38580",
                        "40796",
                        "0.0000",
                        1447632000000
                    ],
                    [
                        "40775",
                        "43223",
                        "40551",
                        "41487",
                        "0.0000",
                        1447718400000
                    ],
                    [
                        "41465",
                        "41778",
                        "40709",
                        "41459",
                        "0.0000",
                        1447804800000
                    ],
                    [
                        "41458",
                        "41547",
                        "39935",
                        "40070",
                        "0.0000",
                        1447891200000
                    ],
                    [
                        "40143",
                        "40293",
                        "38098",
                        "39545",
                        "0.0000",
                        1447977600000
                    ],
                    [
                        "39545",
                        "40392",
                        "39113",
                        "40093",
                        "0.0000",
                        1448064000000
                    ],
                    [
                        "40093",
                        "40105",
                        "39310",
                        "39856",
                        "0.0000",
                        1448150400000
                    ],
                    [
                        "39873",
                        "40050",
                        "39446",
                        "39772",
                        "0.0000",
                        1448236800000
                    ],
                    [
                        "39747",
                        "39747",
                        "38918",
                        "39170",
                        "0.0000",
                        1448323200000
                    ],
                    [
                        "39144",
                        "40606",
                        "38659",
                        "40350",
                        "0.0000",
                        1448409600000
                    ],
                    [
                        "40329",
                        "45317",
                        "40283",
                        "43318",
                        "0.0000",
                        1448496000000
                    ],
                    [
                        "43422",
                        "44725",
                        "42645",
                        "43849",
                        "0.0000",
                        1448582400000
                    ],
                    [
                        "43883",
                        "44131",
                        "43023",
                        "43826",
                        "0.0000",
                        1448668800000
                    ],
                    [
                        "43805",
                        "45836",
                        "43519",
                        "45631",
                        "0.0000",
                        1448755200000
                    ],
                    [
                        "45548",
                        "47139",
                        "45182",
                        "46442",
                        "0.0000",
                        1448841600000
                    ],
                    [
                        "46395",
                        "46678",
                        "43582",
                        "44624",
                        "0.0000",
                        1448928000000
                    ],
                    [
                        "44558",
                        "44807",
                        "42858",
                        "44230",
                        "0.0000",
                        1449014400000
                    ],
                    [
                        "44271",
                        "45721",
                        "43977",
                        "44329",
                        "0.0000",
                        1449100800000
                    ],
                    [
                        "44350",
                        "44852",
                        "43636",
                        "44768",
                        "0.0000",
                        1449187200000
                    ],
                    [
                        "44768",
                        "48003",
                        "44692",
                        "47768",
                        "0.0000",
                        1449273600000
                    ],
                    [
                        "47770",
                        "49229",
                        "47154",
                        "47831",
                        "0.0000",
                        1449360000000
                    ],
                    [
                        "47874",
                        "49362",
                        "46946",
                        "48773",
                        "0.0000",
                        1449446400000
                    ],
                    [
                        "48764",
                        "51493",
                        "47814",
                        "51373",
                        "0.0000",
                        1449532800000
                    ],
                    [
                        "51220",
                        "52110",
                        "48559",
                        "50744",
                        "0.0000",
                        1449619200000
                    ],
                    [
                        "50613",
                        "50922",
                        "49785",
                        "50577",
                        "0.0000",
                        1449705600000
                    ],
                    [
                        "50673",
                        "54996",
                        "50620",
                        "54821",
                        "0.0000",
                        1449792000000
                    ],
                    [
                        "54831",
                        "56608",
                        "48766",
                        "52782",
                        "0.0000",
                        1449878400000
                    ],
                    [
                        "52769",
                        "53603",
                        "51069",
                        "52355",
                        "0.0000",
                        1449964800000
                    ],
                    [
                        "52312",
                        "54063",
                        "51743",
                        "53700",
                        "0.0000",
                        1450051200000
                    ],
                    [
                        "53712",
                        "56600",
                        "53669",
                        "56522",
                        "0.0000",
                        1450137600000
                    ],
                    [
                        "56554",
                        "56604",
                        "53259",
                        "55838",
                        "0.0000",
                        1450224000000
                    ],
                    [
                        "55800",
                        "56210",
                        "55003",
                        "55860",
                        "0.0000",
                        1450310400000
                    ],
                    [
                        "55770",
                        "56644",
                        "55184",
                        "56068",
                        "0.0000",
                        1450396800000
                    ],
                    [
                        "56183",
                        "56450",
                        "54769",
                        "55953",
                        "0.0000",
                        1450483200000
                    ],
                    [
                        "55964",
                        "55977",
                        "52564",
                        "53678",
                        "0.0000",
                        1450569600000
                    ],
                    [
                        "53645",
                        "54137",
                        "51559",
                        "53098",
                        "0.0000",
                        1450656000000
                    ],
                    [
                        "53124",
                        "53678",
                        "52405",
                        "52705",
                        "0.0000",
                        1450742400000
                    ],
                    [
                        "52716",
                        "53872",
                        "52569",
                        "53528",
                        "0.0000",
                        1450828800000
                    ],
                    [
                        "53551",
                        "55315",
                        "53551",
                        "54729",
                        "0.0000",
                        1450915200000
                    ],
                    [
                        "54823",
                        "55129",
                        "53887",
                        "54790",
                        "0.0000",
                        1451001600000
                    ],
                    [
                        "54789",
                        "55023",
                        "48985",
                        "50205",
                        "0.0000",
                        1451088000000
                    ],
                    [
                        "50171",
                        "51171",
                        "49376",
                        "50716",
                        "0.0000",
                        1451174400000
                    ],
                    [
                        "50798",
                        "51788",
                        "50189",
                        "50721",
                        "0.0000",
                        1451260800000
                    ],
                    [
                        "50646",
                        "52228",
                        "50389",
                        "52046",
                        "0.0000",
                        1451347200000
                    ],
                    [
                        "52033",
                        "52425",
                        "50732",
                        "51297",
                        "0.0000",
                        1451433600000
                    ],
                    [
                        "51327",
                        "52156",
                        "50569",
                        "51796",
                        "0.0000",
                        1451520000000
                    ]
                ]
            }
        ],
        "timestamp": 1486989440462
    }
}